<?xml version="1.0" encoding="UTF-8"?>
<orders>
	<order>
		<type>GPU</type>
		<title>Gigabyte Windforce Radeon R9</title>
		<model>290 x</model>
	</order>
	<order>
		<type>GPU</type>
		<title>MSI Radeon R9</title>
		<model>280 x</model>
	</order>
	<order>
		<type>CPU</type>
		<title>Intel Core i7</title>
		<model>5960</model>
	</order>
	<order>
		<type>Graphics Card</type>
		<title>ASUS Radeon R9</title>
		<model>380 x</model>
	</order>
	<order>
		<type>testq</type>
		<title>test</title>
		<model>qtesfdf</model>
	</order>
	<order>
		<type></type>
		<title></title>
		<model></model>
	</order>
	<order>
		<type></type>
		<title></title>
		<model></model>
	</order>
	<order>
		<type></type>
		<title></title>
		<model></model>
	</order>
	<order>
		<type></type>
		<title></title>
		<model></model>
	</order>
	<order>
		<type></type>
		<title></title>
		<model></model>
	</order>
</orders>